aioetherscan/__init__.py
aioetherscan/client.py
aioetherscan/common.py
aioetherscan/exceptions.py
aioetherscan/modules/account.py
aioetherscan/modules/base.py
aioetherscan/modules/block.py
aioetherscan/modules/contract.py
aioetherscan/modules/extra/__init__.py
aioetherscan/modules/extra/contract.py
aioetherscan/modules/extra/generators/blocks_parser.py
aioetherscan/modules/extra/generators/blocks_range.py
aioetherscan/modules/extra/generators/generator_utils.py
aioetherscan/modules/extra/generators/helpers.py
aioetherscan/modules/extra/link.py
aioetherscan/modules/gas_tracker.py
aioetherscan/modules/logs.py
aioetherscan/modules/proxy.py
aioetherscan/modules/stats.py
aioetherscan/modules/token.py
aioetherscan/modules/transaction.py
aioetherscan/network.py
aioetherscan/url_builder.py
aioetherscan-0.9.4.dist-info/LICENSE
aioetherscan-0.9.4.dist-info/METADATA
aioetherscan-0.9.4.dist-info/WHEEL
aioetherscan-0.9.4.dist-info/RECORD
